cpsamd_kernel/__init__.py
cpsamd_kernel/__main__.py
cpsamd_kernel/cpsamd.py
cpsamd_kernel/install.py
cpsamd_kernel/kernel.py
cpsamd_kernel-0.1.dist-info/WHEEL
cpsamd_kernel-0.1.dist-info/METADATA
cpsamd_kernel-0.1.dist-info/RECORD
