Metadata-Version: 1.2
Name: cpsamd_kernel
Version: 0.1
Summary: A Jupyter kernel for CircuitPython on CPSAMD
Home-page: https://github.com/willingc/cpsamd_kernel
License: UNKNOWN
Author: Carol Willing
Author-email: willingc@willingconsulting.com
Requires-Python: >=3
Classifier: License :: OSI Approved :: MIT License
Classifier: Framework :: IPython
Classifier: Intended Audience :: Developers
Classifier: Intended Audience :: Education
Classifier: Programming Language :: Python :: 3
Classifier: Topic :: Education
Classifier: Topic :: Software Development :: Embedded Systems
Classifier: Development Status :: 2 - Pre-Alpha
Classifier: Environment :: MacOS X
Requires-Dist: pyserial
Requires-Dist: ipykernel
